[
  {
    "id": 273,
    "name": "江宁区",
    "city": "南京市",
    "subAreas": [
      {
        "name": "东山镇",
        "city": "南京市",
        "poi": "南京江宁区东山镇"
      },
      {
        "name": "南京市江宁区汤山镇",
        "city": "",
        "poi": ""
      },
      {
        "name": "开发区",
        "city": "南京市",
        "poi": "南京江宁区开发区"
      },
      {
        "name": "南京市江宁区江宁大学城",
        "city": "",
        "poi": ""
      },
      {
        "name": "南京市江宁区同曦/瑞都商业圈",
        "city": "",
        "poi": ""
      },
      {
        "name": "南京市江宁区江宁万达",
        "city": "",
        "poi": ""
      },
      {
        "name": "南京市江宁区禄口机场",
        "city": "",
        "poi": ""
      },
      {
        "name": "南京市江宁区胜太路沿线",
        "city": "",
        "poi": ""
      },
      {
        "name": "南京市江宁区将军大道沿线",
        "city": "",
        "poi": ""
      },
      {
        "name": "南京市江宁区江宁百家湖",
        "city": "",
        "poi": ""
      },
      {
        "name": "南京市江宁区铜山镇",
        "city": "",
        "poi": ""
      },
      {
        "name": "南京市江宁区金轮新都汇/欧尚",
        "city": "",
        "poi": ""
      },
      {
        "name": "南京市江宁区托乐嘉",
        "city": "",
        "poi": ""
      },
      {
        "name": "南京市江宁区殷巷",
        "city": "",
        "poi": ""
      },
      {
        "name": "南京市江宁区众彩市场",
        "city": "",
        "poi": ""
      },
      {
        "name": "南京市江宁区南京南站/喜马拉雅",
        "city": "",
        "poi": ""
      },
      {
        "name": "南京市江宁区江宁弘阳生活广场",
        "city": "",
        "poi": ""
      },
      {
        "name": "南京市江宁区湖熟镇",
        "city": "",
        "poi": ""
      },
      {
        "name": "南京市江宁区濮塘风景区",
        "city": "",
        "poi": ""
      },
      {
        "name": "南京市江宁区砂之船奥莱",
        "city": "",
        "poi": ""
      },
      {
        "name": "南京市江宁区谷里",
        "city": "",
        "poi": ""
      },
      {
        "name": "南京市江宁区九龙湖滨天地",
        "city": "",
        "poi": ""
      },
      {
        "name": "南京市江宁区义乌小商品城",
        "city": "",
        "poi": ""
      },
      {
        "name": "南京市江宁区岔路口",
        "city": "",
        "poi": ""
      },
      {
        "name": "南京市江宁区将军山",
        "city": "",
        "poi": ""
      },
      {
        "name": "南京市江宁区河定桥",
        "city": "",
        "poi": ""
      },
      {
        "name": "南京市江宁区江宁滨江开发区",
        "city": "",
        "poi": ""
      },
      {
        "name": "南京市江宁区百家湖",
        "city": "",
        "poi": ""
      },
      {
        "name": "南京市江宁区麒麟门",
        "city": "",
        "poi": ""
      },
      {
        "name": "南京市江宁区江宁科学园",
        "city": "",
        "poi": ""
      },
      {
        "name": "南京市江宁区竹山路沿线",
        "city": "",
        "poi": ""
      }
    ]
  },

  {
    "id": 62,
    "name": "鼓楼区",
    "subAreas": [
      {
        "id": 62,
        "name": "全部"
      },
      {
        "id": 830,
        "name": "山西路/湖南路"
      },
      {
        "id": 837,
        "name": "南大/南师大"
      },
      {
        "id": 838,
        "name": "南京艺术学院/龙江"
      },
      {
        "id": 841,
        "name": "南京西站/阅江楼"
      },
      {
        "id": 842,
        "name": "三牌楼"
      },
      {
        "id": 8344,
        "name": "鼓楼广场"
      },
      {
        "id": 13319,
        "name": "新街口/五台山体育中心"
      },
      {
        "id": 15583,
        "name": "五塘村"
      },
      {
        "id": 15585,
        "name": "热河南路/三汊河"
      },
      {
        "id": 15587,
        "name": "幕府西路"
      },
      {
        "id": 15588,
        "name": "金陵小区"
      },
      {
        "id": 15589,
        "name": "建宁路"
      },
      {
        "id": 15591,
        "name": "大桥南路"
      },
      {
        "id": 15627,
        "name": "南瑞路/新模范马路"
      },
      {
        "id": 18076,
        "name": "新城市广场"
      },
      {
        "id": 18077,
        "name": "环宇城"
      },
      {
        "id": 38660,
        "name": "小市"
      },
      {
        "id": 40328,
        "name": "清江苏宁广场"
      },
      {
        "id": 41479,
        "name": "凤凰西街"
      },
      {
        "id": 41561,
        "name": "草场门/龙江"
      },
      {
        "id": 41641,
        "name": "清凉门大街"
      },
      {
        "id": 43095,
        "name": "紫峰购物广场"
      },
      {
        "id": 46130,
        "name": "新城市/虹桥中心"
      }
    ]
  },
  {
    "id": 63,
    "name": "玄武区",
    "subAreas": [
      {
        "id": 63,
        "name": "全部"
      },
      {
        "id": 840,
        "name": "珠江路沿线"
      },
      {
        "id": 1168,
        "name": "火车站/玄武湖"
      },
      {
        "id": 12467,
        "name": "红山动物园/火车站"
      },
      {
        "id": 12468,
        "name": "明故宫/后宰门"
      },
      {
        "id": 14619,
        "name": "仙鹤门新天地广场"
      },
      {
        "id": 14624,
        "name": "徐庄软件园"
      },
      {
        "id": 15790,
        "name": "艾尚天地/凯润新城"
      },
      {
        "id": 15791,
        "name": "红庙街区"
      },
      {
        "id": 15793,
        "name": "北门桥"
      },
      {
        "id": 15794,
        "name": "四牌楼/成贤街"
      },
      {
        "id": 15795,
        "name": "进香河/老虎桥"
      },
      {
        "id": 15796,
        "name": "丹凤街"
      },
      {
        "id": 15797,
        "name": "大行宫"
      },
      {
        "id": 15798,
        "name": "总统府/1912商圈"
      },
      {
        "id": 15799,
        "name": "高楼门"
      },
      {
        "id": 15801,
        "name": "锁金村/南京林业大学"
      },
      {
        "id": 15802,
        "name": "曼度嘉年华/长江路"
      },
      {
        "id": 15803,
        "name": "北京东路"
      },
      {
        "id": 15804,
        "name": "樱驼花园/花园路"
      },
      {
        "id": 15805,
        "name": "营苑北路/墨香路"
      },
      {
        "id": 15813,
        "name": "卫岗/下马坊"
      },
      {
        "id": 15814,
        "name": "孝陵卫/森林摩尔"
      },
      {
        "id": 15815,
        "name": "钟学北路/南湾营"
      },
      {
        "id": 40454,
        "name": "环亚凯瑟琳广场"
      },
      {
        "id": 42002,
        "name": "森林摩尔商业街区"
      },
      {
        "id": 45739,
        "name": "君临紫金商业街"
      }
    ]
  },
  {
    "id": 64,
    "name": "建邺区",
    "subAreas": [
      {
        "id": 64,
        "name": "全部"
      },
      {
        "id": 846,
        "name": "莫愁湖/水西门"
      },
      {
        "id": 4736,
        "name": "河西"
      },
      {
        "id": 9620,
        "name": "奥体中心"
      },
      {
        "id": 13267,
        "name": "茶南美食/万达金街"
      },
      {
        "id": 13268,
        "name": "应天大街/文体路"
      },
      {
        "id": 15584,
        "name": "国际博览中心/元通"
      },
      {
        "id": 15586,
        "name": "油坊桥/天迈广场"
      },
      {
        "id": 15590,
        "name": "雨润大街"
      },
      {
        "id": 15599,
        "name": "中央商场/嘉业国际"
      },
      {
        "id": 36591,
        "name": "万达广场"
      },
      {
        "id": 42265,
        "name": "集庆门大街"
      }
    ]
  },
  {
    "id": 66,
    "name": "秦淮区",
    "subAreas": [
      {
        "id": 66,
        "name": "全部"
      },
      {
        "id": 839,
        "name": "瑞金路沿线"
      },
      {
        "id": 844,
        "name": "苜蓿园"
      },
      {
        "id": 845,
        "name": "升州路/集庆路"
      },
      {
        "id": 831,
        "name": "新街口地区"
      },
      {
        "id": 832,
        "name": "夫子庙/水游城"
      },
      {
        "id": 843,
        "name": "常府街/长白街"
      },
      {
        "id": 1172,
        "name": "秦虹/大明路"
      },
      {
        "id": 13085,
        "name": "新街口/德基广场"
      },
      {
        "id": 44460,
        "name": "秦虹村/中华门"
      },
      {
        "id": 45959,
        "name": "夫子庙地区"
      }
    ]
  },
  {
    "id": 833,
    "name": "栖霞区",
    "subAreas": [
      {
        "id": 833,
        "name": "全部"
      },
      {
        "id": 9279,
        "name": "马群街道"
      },
      {
        "id": 9280,
        "name": "仙林大学城"
      },
      {
        "id": 9281,
        "name": "迈皋桥老街"
      },
      {
        "id": 14605,
        "name": "爱尚街区"
      },
      {
        "id": 14613,
        "name": "学则路"
      },
      {
        "id": 14614,
        "name": "百水芊城"
      },
      {
        "id": 14615,
        "name": "亚东商业广场"
      },
      {
        "id": 14616,
        "name": "南邮广场"
      },
      {
        "id": 14617,
        "name": "曼度商业街区"
      },
      {
        "id": 14618,
        "name": "大成名店"
      },
      {
        "id": 14620,
        "name": "仙林新村"
      },
      {
        "id": 14621,
        "name": "南大和园"
      },
      {
        "id": 14622,
        "name": "金鹰奥莱城"
      },
      {
        "id": 14623,
        "name": "东城汇"
      },
      {
        "id": 14677,
        "name": "华电西路"
      },
      {
        "id": 14679,
        "name": "长营村"
      },
      {
        "id": 14680,
        "name": "和燕路"
      },
      {
        "id": 14693,
        "name": "万寿商业街"
      },
      {
        "id": 14694,
        "name": "摄山"
      },
      {
        "id": 14695,
        "name": "燕子矶"
      },
      {
        "id": 14696,
        "name": "晓庄广场"
      },
      {
        "id": 14697,
        "name": "万兴路"
      },
      {
        "id": 14698,
        "name": "尧化门街区"
      },
      {
        "id": 23352,
        "name": "万谷慧生活广场"
      },
      {
        "id": 23372,
        "name": "新港开发区"
      },
      {
        "id": 25639,
        "name": "丁家庄商业街区"
      },
      {
        "id": 44077,
        "name": "栖霞街道"
      },
      {
        "id": 45871,
        "name": "晓庄彩虹广场"
      }
    ]
  },
  {
    "id": 835,
    "name": "六合区",
    "subAreas": [
      {
        "id": 835,
        "name": "全部"
      },
      {
        "id": 13499,
        "name": "葛塘商圈"
      },
      {
        "id": 13502,
        "name": "园林商圈"
      },
      {
        "id": 15131,
        "name": "紫晶广场"
      },
      {
        "id": 24680,
        "name": "龙池/时代广场"
      },
      {
        "id": 24681,
        "name": "凤凰山公园"
      },
      {
        "id": 24744,
        "name": "金宁广场"
      },
      {
        "id": 24755,
        "name": "龙海商圈"
      },
      {
        "id": 24756,
        "name": "秦苑路"
      },
      {
        "id": 24757,
        "name": "西门"
      },
      {
        "id": 24758,
        "name": "瓜埠"
      },
      {
        "id": 28237,
        "name": "BHG华联"
      },
      {
        "id": 28238,
        "name": "阿卡商业街"
      },
      {
        "id": 28239,
        "name": "南钢/凤南创业街"
      },
      {
        "id": 28240,
        "name": "平顶山路/扬子"
      },
      {
        "id": 28365,
        "name": "玉桥商圈"
      },
      {
        "id": 28412,
        "name": "龙袍镇"
      },
      {
        "id": 28413,
        "name": "横梁镇商圈"
      },
      {
        "id": 28414,
        "name": "程桥商圈"
      },
      {
        "id": 38633,
        "name": "玉桥市场"
      },
      {
        "id": 38888,
        "name": "新华西路"
      },
      {
        "id": 39022,
        "name": "大厂十村"
      },
      {
        "id": 39059,
        "name": "阿尔卡迪亚"
      },
      {
        "id": 39112,
        "name": "新华东路"
      },
      {
        "id": 42921,
        "name": "雄州"
      },
      {
        "id": 43075,
        "name": "大厂"
      }
    ]
  },
  {
    "id": 834,
    "name": "雨花台区",
    "subAreas": [
      {
        "id": 834,
        "name": "全部"
      },
      {
        "id": 9308,
        "name": "虹悦城"
      },
      {
        "id": 12887,
        "name": "铁心桥/楚翘城"
      },
      {
        "id": 12888,
        "name": "南京南站/明发"
      },
      {
        "id": 14325,
        "name": "板桥"
      },
      {
        "id": 14857,
        "name": "西善桥/油坊桥"
      },
      {
        "id": 14858,
        "name": "安德门/小行"
      },
      {
        "id": 17258,
        "name": "紫荆广场/宜家"
      },
      {
        "id": 19579,
        "name": "梅山"
      },
      {
        "id": 37896,
        "name": "岱山新城"
      },
      {
        "id": 46126,
        "name": "铁心桥/三江学院"
      }
    ]
  },
  {
    "id": 1063,
    "name": "浦口区",
    "subAreas": [
      {
        "id": 1063,
        "name": "全部"
      },
      {
        "id": 13493,
        "name": "澳林广场"
      },
      {
        "id": 13494,
        "name": "弘阳广场/印象汇"
      },
      {
        "id": 13495,
        "name": "公园北路"
      },
      {
        "id": 13496,
        "name": "金浦购物中心"
      },
      {
        "id": 13497,
        "name": "明发外滩广场"
      },
      {
        "id": 13501,
        "name": "凤凰大街"
      },
      {
        "id": 21107,
        "name": "大华家乐福"
      },
      {
        "id": 23327,
        "name": "华侨城"
      },
      {
        "id": 25650,
        "name": "天润城/天悦城"
      },
      {
        "id": 27127,
        "name": "南京信息工程大学"
      },
      {
        "id": 27128,
        "name": "慕斯荟"
      },
      {
        "id": 38568,
        "name": "高新区"
      },
      {
        "id": 38906,
        "name": "江浦"
      },
      {
        "id": 38996,
        "name": "明发城市广场"
      },
      {
        "id": 39152,
        "name": "威尼斯水城"
      },
      {
        "id": 39282,
        "name": "汤泉社区"
      },
      {
        "id": 39294,
        "name": "南大金陵学院"
      },
      {
        "id": 40298,
        "name": "明发滨江"
      },
      {
        "id": 46009,
        "name": "老浦口1914"
      }
    ]
  },
  {
    "id": 2709,
    "name": "高淳区",
    "subAreas": [
      {
        "id": 2709,
        "name": "全部"
      },
      {
        "id": 38409,
        "name": "固城镇"
      },
      {
        "id": 38474,
        "name": "东坝镇"
      },
      {
        "id": 38602,
        "name": "桠溪镇"
      },
      {
        "id": 38635,
        "name": "古柏镇"
      },
      {
        "id": 38657,
        "name": "漆桥镇"
      },
      {
        "id": 38755,
        "name": "高淳区中心城区"
      },
      {
        "id": 38902,
        "name": "砖墙镇"
      },
      {
        "id": 38944,
        "name": "阳江镇"
      },
      {
        "id": 39147,
        "name": "国际慢城"
      },
      {
        "id": 41344,
        "name": "中山步行街"
      },
      {
        "id": 42014,
        "name": "北岭路沿线"
      },
      {
        "id": 42288,
        "name": "镇兴路沿线"
      },
      {
        "id": 42299,
        "name": "富克斯广场"
      },
      {
        "id": 42522,
        "name": "大山风景区"
      },
      {
        "id": 43364,
        "name": "高淳老街"
      },
      {
        "id": 44506,
        "name": "宝塔路沿线"
      },
      {
        "id": 45213,
        "name": "云鼎时尚街区"
      },
      {
        "id": 46127,
        "name": "固城湖路沿线"
      }
    ]
  },
  {
    "id": 836,
    "name": "溧水区",
    "subAreas": [
      {
        "id": 836,
        "name": "全部"
      },
      {
        "id": 17528,
        "name": "通济街商业广场"
      },
      {
        "id": 35257,
        "name": "万辰广场"
      },
      {
        "id": 35260,
        "name": "广成/荣昌"
      },
      {
        "id": 35262,
        "name": "康利广场/康利华府"
      },
      {
        "id": 36142,
        "name": "影都商汇"
      },
      {
        "id": 38351,
        "name": "万达广场"
      },
      {
        "id": 38478,
        "name": "石湫镇"
      },
      {
        "id": 38533,
        "name": "和凤镇"
      },
      {
        "id": 38605,
        "name": "弯子口"
      },
      {
        "id": 38724,
        "name": "大西门"
      },
      {
        "id": 38746,
        "name": "晶桥镇"
      },
      {
        "id": 38778,
        "name": "大东门"
      },
      {
        "id": 38836,
        "name": "洪蓝镇"
      },
      {
        "id": 38842,
        "name": "顾家欧亚达"
      },
      {
        "id": 38892,
        "name": "傅家边草莓园"
      },
      {
        "id": 39000,
        "name": "白马镇"
      },
      {
        "id": 39005,
        "name": "柘塘镇"
      },
      {
        "id": 39036,
        "name": "东屏镇"
      },
      {
        "id": 39051,
        "name": "南门口"
      },
      {
        "id": 39055,
        "name": "周园"
      },
      {
        "id": 39081,
        "name": "新车站"
      },
      {
        "id": 39142,
        "name": "溧水开发区"
      },
      {
        "id": 39297,
        "name": "视觉艺术学院"
      },
      {
        "id": 39734,
        "name": "海乐城"
      },
      {
        "id": 39769,
        "name": "时代广场"
      },
      {
        "id": 41878,
        "name": "宝塔路/万辰苏果"
      }
    ]
  }
]
